{"task_type": "solve", "max_assigns": 3, "reward_dollars": "0.03", "title": "GVLAB: Visual Associations - (solve items 0-100)", "keywords": "Fun, Association, Creativity, Visual Associations, Find Associations", "description": "Fun Visual Associations: Given 5 images, choose the images that are most associated with the cue - To practice, visit https://gvlab-dataset.github.io/beat-the-ai, 'Guess The Associations' practice", "current_time": "2022-05-06_01:21:31", "is_sandbox": false, "start_idx": 0, "end_idx": 100, "gvlab_hit_type_id": "36R4ILE2GAQ1OZ6Z7L174EFT51AFHG", "current_mturk_balance": "2255.81", "hit_responses": ["3FHTJGYT8NMGQOSZ7Q9DBSO5KCUPGZ", "3MA5N0ATTCXBCJLJ938N1EOUKQEKWS", "3GITHABACY7Q898FSWBW5ZP9AEON2I", "3YLPJ8OXX8Z5NH16YGHTWGD5W6UX48", "3YLTXLH3DFSUQKNARWRVWS06ZC7PHY", "307L9TDWJYEFTR4YWWP1O9U1GSON3T", "3IWA71V4TI2J245KH4A8TEXJSX0X6T", "375VSR8FVWV1TI3JAA1R1U4QWKCZRQ", "3PZDSVZ3J530BNN2WAUKYEM7USKN4E", "32L724R85L6UMFYUXE9GW41LZPMPIR", "371Q3BEXDHVDUX3WPZ1WR49MIMVZSE", "31YWE12TE0Y264JP0EF0ZSXFN8KX7S", "3EAWOID6MTJWK4EAF0T9WSQ7ZJ6V0N", "32ZCLEW0BZ6QHQI0FWUG85GLC4BPJ3", "33W1NHWFYH7E9XGBEZ6M1958K59ZT3", "33K3E8REWWH66IO8AJ76DSTAYSQX8F", "3CVDZS288HM4RLZR4QB3C3UYESJFMU", "3DWGDA5POFQWRTZSBJX9AX9H4BCV1Q", "3G4VVJO6PZ2LSAOIXHUS9KGYRTBPK2", "3M0556243S6A93KRGRQ3PIJYJITFNU", "3LN50BUKPVXWCG60IH6TOKTDGTGPL5", "3SSN80MU8CAQ1JQ9J8493X21TSKKXL", "3HRWUH63QUOI76R2AFDU36SLUOFN5J", "34XASH8KLQ8GIYOLIT78OX82GY6PM7", "39AYGO6AFF6EQARGFYNZVC6LQJQN6Z", "3WRAAIUSBJLKP6HN7HRK9JZ5OGQXAJ", "3M93N4X8HK9NUIYS7DYA3ALWZOISJM", "3Y7LTZE0YT8T9AV0E4WW65RA3JGZUU", "3WYZV0QBFJZP8GMFDVRG4UJB6YBXBE", "3E22YV8GG1SM0G9LUUM81CX2LOGPN7", "3RSBJ6YZECCSROK3H6QG47J39SYFO9", "39RRBHZ0AUNTMPK0JU612RTTHQPZVJ", "3AA88CN98PPF1OGJO4QBMB9AVYEKYR", "33NKDW9FFX48ILELRVNBFEPTOJBXCL", "3JYPJ2TAYIUACOW4W63VT7OTJXUFPQ", "30EMX9PEVK5I524APYYM4PL9EDISKL", "3TX9T2ZCB9N61EK594BXOTC7OZRZWT", "3S829FDFT2NINDKZRRIMZK7B9JNXDL", "3SCKNODZ0X2XUA5LY8SR1Q6HLUAN7Y", "3TCFMTM8HEANU21QN9DY8SC67DK21Q", "3ZFRE2BDQ90LQEPVJ97JQCQEX1XZXM", "3DQYSJDTYLXNFJYZNMT652PW9VOXEE", "3JU8CV4BRLY4I19XV9MLG1X7BYLPOM", "3FW4EL5A3LAUJNJM6DDCDBMBZJY227", "3PCPFX4U40CVC0XJWJIKTCE3OTGFQH", "3ZG552ORAMQ3GEHOUNXNFGJMWHQV27", "3O71U79SRBBDVQ4DAAB2J2DD3IDSMQ", "3B0MCRZMBRGM31LYA9Z0512XL3HPP3", "33CLA8O0MIXVO1CJ9Y7KY2O8KFIFRI", "3UYRNV2KITL1UOA48DKXFQ2CWEGN8L", "3SV8KD29L4EF6EQOKQSU0IIC1SIKZI", "3VMHWJRYHV2FLXYVIXDCNKAWLW3XFW", "3ZLW647WALHJ45F5ADRHWLR35XY23I", "3HEM8MA6H9Y73DMDAMEP56S7QZ3PQU", "3ZICQFRS314AV9PAKRV4NX6P51VZZJ", "3YCT0L9OMMVJD8PDMBQ2WH2D88NSNQ", "39KMGHJ4RZWGR3DUC35KBZ0H5NU001", "3G5RUKN2ECP18TTED5QBFMXNGKYN9A", "3ODOP6T3AS64M1Y9ARW06QJ9JXU243", "338GLSUI43X7PGCWON7POCT46H1FS6", "3J5XXLQDHMXS1WD7YNBSYQOE2VQV3I", "334ZEL5JX611VTPPNQQFB62IYISSO5", "3R5LWXWHR0ULZXUQTHJU55A8MB3XGV", "3G57RS03HHRMIK29OWFABIPNJTP258", "3A9LA2FRWS0ZZTP1DN1CQ5M91BGXHU", "38XPGNCKHTMDJSWBY1GB8VGKGVMV43", "32XN26MTXZ5TOZ2G1WR39JS58L4L0U", "3VEI3XUCZRJ7FE1DN13PAW2CML5PRV", "3E9ZFLPWOYEZVO0LJ5JXQHNO1OVXIN", "30P8I9JKOI7VFB0BC6ZLDNMYGRHV58", "386659BNTL3GYSYC8M9KP4JRAF0014", "38O9DZ0A629I1O2NTFPF3O3NFO026O", "3EN4YVUOUCEVQZKR1N4X2I2OE3KXJZ", "3RQVKZ7ZRK515OGSCPU7923JAZK27N", "31J7RYECZLCTVONYXFV3NOBFDDAL1X", "3TC2K6WK9GO552LBMUMDN2ZELJQ28A", "3SSN80MU8CAQ1JQ9J8493X21TSKXKY", "3VADEH0UHCJJGT1Q2Q3U06788NOSPM", "3UQVX1UPFS3NNDG8RQ9YUNTW2LE02L", "3N5YJ55YXGPFDC3J5B4BBH87M2GNAP", "3FJ2RVH25ZS5J74LRMSRNYUP5P829Z", "3XBXDSS88851LP8R48GAIXFGISPXL1", "3N3WJQXELSC0K95UGJVHS7LK5JOL2E", "3S8A4GJRD3PRYF0PHP9Q5T0YCMSV6O", "3MJ9GGZYO3SJOQEQJS6RJT59B7Q2AE", "3GL25Y6843GLR7QC4KHPIAU5IXFXM3", "3BAWBGQGYLLA2FEU0ZEIB70U7XCV7N", "322ZSN9Z5G6Y60SMT6GW7DSZJA74TX", "3EFNPKWBMSAC8VCRVQN3DXYO8ZE03W", "3NCN4N1H1G3KWM8BBP476SSD4K1NBK", "3MQY1YVHS36O70JIP66NE4PFTPB2B9", "31ODACBENU14G52523IJ0BXIDJASQD", "3QQUBC64ZE0R9PBCGLWPVPJ5NNPXN3", "3DW3BNF1GH4E2TJDA46OP7WPIHIV8A", "3TFJJUELSHB7H5BO362IPOVXBAB2CG", "337F8MIIMZZXQRVVV4SMN2QUMZA04H", "3FO95NVK5CM4S6H5FI7J517N95CSRE", "3Z33IC0JC08EGY2NFWC2P3R02N0V9Z", "3R5OYNIC2CVKVTE5RQ8KAB3UA62PT8", "3VZYA8PITOKFMAZV99BWSUW8MV505M"], "current_mturk_balance_after_hits": "2243.81"}