{
  "task_type": "solve",
  "reward_dollars": "0.03",
  "title": "GVLAB: Visual Associations - (solve items 0-100)",
  "keywords": "Fun, Association, Creativity, Visual Associations, Find Associations",
  "description": "Fun Visual Associations: Given 5 images, choose the images that are most associated with the cue",
  "current_time": "2022-05-03_20:51:39",
  "is_sandbox": true,
  "start_idx": 0,
  "end_idx": 100,
  "gvlab_hit_type_id": "3DCJP2JIFL2FRFFQ1YM56ARCF5J3C1",
  "current_mturk_balance": {
    "AvailableBalance": "10000.00",
    "ResponseMetadata": {
      "RequestId": "ce5eac3a-93fe-4fc1-8fac-02bd8642c183",
      "HTTPStatusCode": 200,
      "HTTPHeaders": {
        "x-amzn-requestid": "ce5eac3a-93fe-4fc1-8fac-02bd8642c183",
        "content-type": "application/x-amz-json-1.1",
        "content-length": "31",
        "date": "Tue, 03 May 2022 20:51:41 GMT"
      },
      "RetryAttempts": 0
    }
  },
  "max_assigns": 1,
  "hit_responses": [
    "3S829FDFT2NINDKZRRIODG58WDGDX7",
    "3TKSOBLOHL2IVDJE8ZZ0TTQGAPGBBP",
    "3V7ICJJAZA2YAEY5TKPDLFKA0XZ4BC",
    "3HO4MYYR12ARL0BPCZZNN3WCL9C6UG",
    "3TRB893CSJWRKIOZB4FYP2VH7CHG7P",
    "3G5RUKN2ECP18TTED5QDTIVK3ER9N2",
    "3AQN9REUTF27NIA9WN4QWUCHYJADYD",
    "309D674SHZ715IBKMZVV4DWYSAGBCW",
    "3S8A4GJRD3PRYF0PHP9SJPYVZGL6V5",
    "3LXX8KJXPWVJQETQEKQQ87VPTOW9OH",
    "3CESM1J3EIP4D40U7ZEO5RH96PN6WF",
    "3SBNLSTU6UR7S8KES969A1LJ4DEDZ4",
    "3VDI8GSXAFFVKWTIL97432RCIWNG8C",
    "3PUV2Q8SV4QBAAHYMVQ6OJEGDASBDW",
    "32W3UF2EZO7HKJQB7KL8WZQSIIZ4CJ",
    "3D3B8GE892D1BE5RTK35X70F3TS9PY",
    "3IWA71V4TI2J245KH4AA7AVGFRT6X8",
    "3RHLQY6EDTQRPBWP7GGJG58A3IB4DJ",
    "3HKIF5DF6YJVY1CSQ1DI3YMN225G91",
    "30EV7DWJTVH829VUM0WCQO2PHXN6YE",
    "3JHB4BPSFKVMBQ66TXIUXCQP8PE9QP",
    "3ICOHX7ENCXFITSOKA41AK0IMIWE06",
    "3ACRLU860N0G2GVYIQ1QU1W1DMTBEP",
    "3IZVJEBJ6A687Z5ZIMYV4VBRNRR6Z5",
    "3OKP4QVBP2J93KMXI7RIZTX78KNGAG",
    "3XH7ZM9YX2GMNRL66C7U220U4BG9RQ",
    "36KM3FWE3RYU9EDEX2QV4A810VS70D",
    "3XD2A6FGFNGYO6LJL17ZSC5QQDZ9SE",
    "3HY86PZXPY4FPID6GT81OPJSRA2E19",
    "3S8APUMBJX588UVUD1LWCJH1PN8BF7",
    "3UV0D2KX1M5ONVALYMB945BVFVR4FU",
    "33IXYHIZB54ME3V2ZX8FT8TXJGGE2Q",
    "3T8DUCXY0NSZ36YYA1CP2H1CSWD9T3",
    "3VGZ74AYTG2XWZJV2LN95ONV8N8GCI",
    "3BFNCI9LYKCQQ6CBGP8E686837C738",
    "3QE4DGPGBRXU1V6G96HRMQB7GAR4GT",
    "3CZH926SIC0WHHAP3BR3MNQV3UCE4M",
    "3OJX0UFJ0ZTE3JDNA62Z7DNEBAK9UU",
    "35JDMRECC4VCTX39YCT4VCNYTZLGEB",
    "307FVKVSYR1B82VFG3DXGDYEH7874T",
    "3Z33IC0JC08EGY2NFWC43ZPXPHT9VJ",
    "34R0BODSP1LED0EPHGADRFW93Q7E5R",
    "39I4RL8QGJ381R1RTCZ97QN8VA44HS",
    "3NFWQRSHVE04ZB35TNDADU8Y500GFT",
    "3SZYX62S5GMT4LZFU8W7L54SH3375Y",
    "3J9L0X0VDF8RVN2S56H0P18BWQV9WT",
    "3OREP8RUT2XEMURPOLREU4HDQ28BG6",
    "3DIIW4IV8PH8XMCBZUHU72ONVNJ4IL",
    "3JY0Q5X05JSADBZ047JSVF8A6F0GGS",
    "3KI0JD2ZU14PNPZTZR6CDBISDYE76E",
    "3FCO4VKOZ4ZT04S859PAPZA5UW2E76",
    "33KMQD9OFJ08RPDYI1B4JPIO89Y77D",
    "32204AGAABYOD7UBOD1AGFKBLFDGHR",
    "37VE3DA4YU3SMQM08R9WF4TE52LBH5",
    "356TQKY9XFJCR3IHS63AXPEJJT4780",
    "379OL9DBSS0VKSXSK7ZOAYTR7YV9YS",
    "3R16PJFTS3DZ3H2ZZX26KI30NR84KW",
    "362E9TQF2HCO925VUVJVGRLQLSSGIK",
    "3HYV4299H0IX0IXRFEHG3Z605G8E8T",
    "3PUOXASB57PVPI7XGT17O52TDSZ9ZJ",
    "3WKGUBL7SZ8ANNKHKXE7ZIGFCRD4LZ",
    "3BVS8WK9Q0HSILXKE9RHFGUT5F0BIY",
    "3YD0MU1NC2NQARBWP4NOTGKE9H47A4",
    "335VBRURDJMXENG1K6NU3V1BPMQE9I",
    "30ZKOOGW2WSCZ5WU0O6FS6T16V4A1A",
    "36GJS3V78VCK4DP1CD4VSS0QY7HGJW",
    "3YKP7CX6G21VT1GOVINKOR4KRZP7BZ",
    "3B9XR6P1WEHODWHQWRCHRH9TIUPBJA",
    "3FULMHZ7OUJUT522K9FMZVV4CW34M1",
    "359AP8GAGG6E368U9IJFZBA29KP7C6",
    "3MJ9GGZYO3SJOQEQJS6TXP36Y1IA2R",
    "3A520CCNWNMBJ6Q6CC1UZQCVV48EAX",
    "3PEG1BH7AEDJOGN8ECCTSW96XJPBK9",
    "3PZDSVZ3J530BNN2WAUMCAK4HMD4N1",
    "3UUSLRKAULPO8YE89EEQJHSKUK17D6",
    "3UXQ63NLAA8U8M5QZCOU7WMLMJUBLC",
    "3URJ6VVYUP9IT8NEXPUZRZK97WI4OG",
    "3FCO4VKOZ4ZT04S859PAPZA5UW27EZ",
    "3V0TR1NRVAOTR4TDN6PHQ404IFEA4N",
    "3ACRLU860N0G2GVYIQ1QU1W1DMTEBS",
    "3D7VY91L65JEE4NBZOP9791AMOKBME",
    "3MXX6RQ9EVR0E8ZFCP7EGZPZH1E4PX",
    "3KL228NDMV8FFXVJUY47T703DWHGKV",
    "3X878VYTIE4L6IS40K9G7HV56XH7FH",
    "3NSCTNUR2Z9BNNXD1B8RVW6IIB9A5S",
    "3H1C3QRA015ZCLN4WQXL5L2JV7TECZ",
    "3NCN4N1H1G3KWM8BBP49KOQAREUBNE",
    "3P4C70TRMR3QZ3D1FYG887DI2WMGLY",
    "3TRB893CSJWRKIOZB4FYP2VH7CH7GG",
    "3FBEFUUYRKR76RXR6UIWN2KIE6KA68",
    "36MUZ9VAE6O9HDTIWMSWPRK1G75EDZ",
    "3SBX2M1TKD9LEK0UC2M3G4F9MX04QO",
    "3S4TINXCC092E78NC44MZDQFHOZBOT",
    "38EHZ67RIMEA5LVMFAHN8KS721CGM0",
    "36BTXXLZ2VULQLFUPHB3LUPEIJ24RP",
    "3IJ95K7NDXYGN3GMRBWNLZH77RMGN0",
    "3CVBMEMMXB25KEJAVAXGA27IMCU7HF",
    "367O8HRHKGUXR0F746B8B4UA4LL4SD",
    "3NBFJK3IOH4Y5OGYSQW00OHCX1RGOF",
    "3GVPRXWRPHG5G9UU1SF1AE8XMP97I8"
  ],
  "current_mturk_balance_after_hits": "10000.00"
}